{"categories":[{"name":"Art","subtopics":[{"name":"Music","needsHelp":[],"canHelp":["dpumford"]},{"name":"Drama","needsHelp":[],"canHelp":[]},{"name":"Painting","needsHelp":[],"canHelp":[]}]},{"name":"Science","subtopics":[{"name":"Chemistry","needsHelp":[],"canHelp":[]},{"name":"Physics","needsHelp":[],"canHelp":[]},{"name":"Biology","needsHelp":[],"canHelp":[]}]},{"name":"History","subtopics":[{"name":"American Studies","needsHelp":[],"canHelp":[]},{"name":"Asian Studies","needsHelp":[],"canHelp":[]}]},{"name":"Engineering","subtopics":[{"name":"Computer Science","needsHelp":[],"canHelp":[]},{"name":"Electrical Engineering","needsHelp":[],"canHelp":[]},{"name":"Civil Engineering","needsHelp":[],"canHelp":[]},{"name":"Industrial Engineering","needsHelp":[],"canHelp":[]}]},{"name":"Language","subtopics":[{"name":"Spanish","needsHelp":["dpumford"],"canHelp":[]},{"name":"English","needsHelp":[],"canHelp":["dpumford"]},{"name":"Swahili","needsHelp":[],"canHelp":[]}]},{"name":"Mathematics","subtopics":[{"name":"Calculus","needsHelp":["dpumford"],"canHelp":[]},{"name":"Linear Algebra","needsHelp":[],"canHelp":[]}]}],"catTemplate":{"name":"","subtopics":[]},"topicTemplate":{"name":"","needsHelp":[],"canHelp":[]}}